<Table><Row><id_clients>1</id_clients><nom_clients>Legrand</nom_clients><prenom_clients>Max</prenom_clients><nom_boutique></nom_boutique><id_adresse>1</id_adresse><contact_clients>0606060606</contact_clients><couriel_clients>maxlegrand@hotmail.com</couriel_clients><adhesion>False</adhesion></Row><Row><id_clients>2</id_clients><nom_clients>Latchoumanassamy</nom_clients><prenom_clients>Adithya</prenom_clients><nom_boutique></nom_boutique><id_adresse>2</id_adresse><contact_clients>0652228006</contact_clients><couriel_clients>ladithya@hotmail.com</couriel_clients><adhesion>True</adhesion></Row><Row><id_clients>3</id_clients><nom_clients>Kioulou</nom_clients><prenom_clients>Eléonor</prenom_clients><nom_boutique></nom_boutique><id_adresse>3</id_adresse><contact_clients>0617639849</contact_clients><couriel_clients>kck.eleonor@gmail.com</couriel_clients><adhesion>True</adhesion></Row><Row><id_clients>4</id_clients><nom_clients>Kalbe</nom_clients><prenom_clients>Remi</prenom_clients><nom_boutique></nom_boutique><id_adresse>4</id_adresse><contact_clients>0707070707</contact_clients><couriel_clients>remikable@icloud.com</couriel_clients><adhesion>True</adhesion></Row><Row><id_clients>5</id_clients><nom_clients>Dupont</nom_clients><prenom_clients>Jean</prenom_clients><nom_boutique></nom_boutique><id_adresse>5</id_adresse><contact_clients>0102030405</contact_clients><couriel_clients>dupont.jean@hotmail.com</couriel_clients><adhesion>True</adhesion></Row><Row><id_clients>6</id_clients><nom_clients>Stippane</nom_clients><prenom_clients>Damien</prenom_clients><nom_boutique></nom_boutique><id_adresse>6</id_adresse><contact_clients>0789456321</contact_clients><couriel_clients>stippaneDamien@hotmail.com</couriel_clients><adhesion>True</adhesion></Row><Row><id_clients>7</id_clients><nom_clients>Lejeune</nom_clients><prenom_clients>Bastien</prenom_clients><nom_boutique></nom_boutique><id_adresse>7</id_adresse><contact_clients>0663179523</contact_clients><couriel_clients>lejeune.bastien@edu.devinci.fr</couriel_clients><adhesion>False</adhesion></Row><Row><id_clients>8</id_clients><nom_clients></nom_clients><prenom_clients></prenom_clients><nom_boutique>DECATHLON</nom_boutique><id_adresse>8</id_adresse><contact_clients>014587963214</contact_clients><couriel_clients>deca@decathlon.com</couriel_clients><adhesion>False</adhesion></Row><Row><id_clients>9</id_clients><nom_clients></nom_clients><prenom_clients></prenom_clients><nom_boutique>GO SPORT</nom_boutique><id_adresse>9</id_adresse><contact_clients>0125489632</contact_clients><couriel_clients>go.contact@gosport.com</couriel_clients><adhesion>False</adhesion></Row><Row><id_clients>10</id_clients><nom_clients></nom_clients><prenom_clients></prenom_clients><nom_boutique>SPORT 2000</nom_boutique><id_adresse>10</id_adresse><contact_clients>0125489687</contact_clients><couriel_clients>2000@sport2000.com</couriel_clients><adhesion>False</adhesion></Row><Row><id_clients>11</id_clients><nom_clients></nom_clients><prenom_clients></prenom_clients><nom_boutique>M Ride cycle store</nom_boutique><id_adresse>11</id_adresse><contact_clients>0165847896</contact_clients><couriel_clients>ride@ridecycle.com</couriel_clients><adhesion>False</adhesion></Row></Table>
